config/__init__.py
transformerocr/__init__.py
transformerocr/predict.py
transformerocr/train.py
transformerocr/config/__init__.py
transformerocr/loader/DataLoader.py
transformerocr/loader/__init__.py
transformerocr/model/__init__.py
transformerocr/model/trainer.py
transformerocr/model/transformer.py
transformerocr/model/transformerocr.py
transformerocr/model/vgg.py
transformerocr/model/vocab.py
transformerocr/optim/__init__.py
transformerocr/optim/optim.py
transformerocr/tool/__init__.py
transformerocr/tool/config.py
transformerocr/tool/detector.py
transformerocr/tool/translate.py
transformerocr/tool/utils.py
transformerocr/tool/visualizer.py
transformerocr-0.1.14.dist-info/LICENSE
transformerocr-0.1.14.dist-info/METADATA
transformerocr-0.1.14.dist-info/WHEEL
transformerocr-0.1.14.dist-info/top_level.txt
transformerocr-0.1.14.dist-info/RECORD
