Metadata-Version: 2.1
Name: transformerocr
Version: 0.1.14
Summary: Transformer base text detection
Home-page: https://github.com/pbcquoc/transformerocr
Author: pbcquoc
Author-email: pbcquoc@gmail.com
License: UNKNOWN
Platform: UNKNOWN
Classifier: Programming Language :: Python :: 3
Classifier: License :: OSI Approved :: MIT License
Classifier: Operating System :: OS Independent
Requires-Python: >=3.6
Requires-Dist: einops (==0.2.0)
Requires-Dist: gdown (==3.11.0)
